Workbook

Sheet Start Here
A1: Excel for Finance — Unit D Practice Workbook
A2: Companion to the 'Financial Modeling' unit on the course website.
A4: This unit's sheets are fully worked examples for you to study, trace, and adapt — not fill-in-the-blank exercises.

Sheet D1 Income Statement
A1: D1 · 3-Statement Model — Income Statement
A2: Two-year projection, driven by a growth and margin assumption.
A5: Revenue growth | B5: 0.08
A6: COGS % of revenue | B6: 0.55
A7: OpEx % of revenue | B7: 0.2
A8: Tax rate | B8: 0.21
A9: D&A ($000) | B9: 50 | C9: 55
A10: Interest expense ($000) | B10: 20 | C10: 20
A13: Line item ($000) | B13: Year 1 | C13: Year 2
A14: Revenue | B14: 1000 | C14: =B14*(1+$B$5)
A15: COGS | B15: =-B14*$B$6 | C15: =-C14*$B$6
A16: Gross Profit | B16: =B14+B15 | C16: =C14+C15
A17: Operating Expenses | B17: =-B14*$B$7 | C17: =-C14*$B$7
A18: EBITDA | B18: =B16+B17 | C18: =C16+C17
A19: D&A | B19: =-B9 | C19: =-C9
A20: EBIT | B20: =B18+B19 | C20: =C18+C19
A21: Interest Expense | B21: =-B10 | C21: =-C10
A22: Pretax Income | B22: =B20+B21 | C22: =C20+C21
A23: Tax | B23: =-B22*$B$8 | C23: =-C22*$B$8
A24: Net Income | B24: =B22+B23 | C24: =C22+C23

Sheet D1 Balance Sheet
A1: D1 · 3-Statement Model — Balance Sheet
A2: Retained earnings links from net income; cash links from the cash flow statement.
A5: Beginning common stock ($000) | B5: 300
A6: Beginning retained earnings ($000) | B6: 150
A7: Beginning PP&E, net ($000) | B7: 400
A8: AR, Inventory, AP, Debt — held flat for simplicity ($000)
A9: AR | B9: 120 | C9: 120
A10: Inventory | B10: 90 | C10: 90
A11: AP | B11: -80 | C11: -80
A12: Debt | B12: -250 | C12: -250
A13: Beginning cash ($000) | B13: 170 | C13: Plug so the implied opening balance sheet balances: (AP 80 + Debt 250 + Common Stock 300 + Retained Earnings 150) - (AR 120 + Inventory 90 + PP&E 400) = 170.
A16: Balance Sheet ($000) | B16: Year 1 | C16: Year 2
A17: Cash | B17: ='D1 Cash Flow'!B16 | C17: ='D1 Cash Flow'!C16
A18: AR | B18: =B9 | C18: =C9
A19: Inventory | B19: =B10 | C19: =C10
A20: PP&E, net | B20: =$B$7-'D1 Income Statement'!B9 | C20: =B20-'D1 Income Statement'!C9
A21: Total Assets | B21: =SUM(B17:B20) | C21: =SUM(C17:C20)
A23: AP | B23: =-B11 | C23: =-C11
A24: Debt | B24: =-B12 | C24: =-C12
A25: Total Liabilities | B25: =SUM(B23:B24) | C25: =SUM(C23:C24)
A27: Common Stock | B27: =$B$5 | C27: =$B$5
A28: Retained Earnings | B28: =$B$6+'D1 Income Statement'!B24 | C28: =B28+'D1 Income Statement'!C24
A29: Total Equity | B29: =B27+B28 | C29: =C27+C28
A31: Check: Assets - Liab - Equity | B31: =B21-B25-B29 | C31: =C21-C25-C29

Sheet D1 Cash Flow
A1: D1 · 3-Statement Model — Cash Flow Statement
A2: Reconciles net income to the change in cash; ending cash feeds the balance sheet.
A5: Beginning cash ($000) | B5: ='D1 Balance Sheet'!B13
A8: Cash Flow ($000) | B8: Year 1 | C8: Year 2
A9: Net Income | B9: ='D1 Income Statement'!B24 | C9: ='D1 Income Statement'!C24
A10: Add back D&A | B10: ='D1 Income Statement'!B9 | C10: ='D1 Income Statement'!C9
A11: Change in Working Capital | B11: 0 | C11: 0
A12: CapEx | B12: 0 | C12: 0
A13: Net Change in Cash | B13: =SUM(B9:B12) | C13: =SUM(C9:C12)
A15: Beginning Cash | B15: =$B$5 | C15: =B16
A16: Ending Cash | B16: =B15+B13 | C16: =C15+C13

Sheet D2 DCF Model
A1: D2 · DCF Model
A2: 5-year unlevered free cash flow, discounted, plus a terminal value.
A5: Year 1 Revenue ($000) | B5: 1000
A6: Revenue growth | B6: 0.1
A7: EBIT margin | B7: 0.22
A8: Tax rate | B8: 0.21
A9: D&A % of revenue | B9: 0.05
A10: CapEx % of revenue | B10: 0.06
A11: WACC | B11: 0.09
A12: Terminal growth rate | B12: 0.025
A15: ($000) | B15: Year 1 | C15: Year 2 | D15: Year 3 | E15: Year 4 | F15: Year 5
A16: Revenue | B16: =$B$5 | C16: =B16*(1+$B$6) | D16: =C16*(1+$B$6) | E16: =D16*(1+$B$6) | F16: =E16*(1+$B$6)
A17: EBIT | B17: =B16*$B$7 | C17: =C16*$B$7 | D17: =D16*$B$7 | E17: =E16*$B$7 | F17: =F16*$B$7
A18: NOPAT (after-tax EBIT) | B18: =B17*(1-$B$8) | C18: =C17*(1-$B$8) | D18: =D17*(1-$B$8) | E18: =E17*(1-$B$8) | F18: =F17*(1-$B$8)
A19: + D&A | B19: =B16*$B$9 | C19: =C16*$B$9 | D19: =D16*$B$9 | E19: =E16*$B$9 | F19: =F16*$B$9
A20: - CapEx | B20: =-B16*$B$10 | C20: =-C16*$B$10 | D20: =-D16*$B$10 | E20: =-E16*$B$10 | F20: =-F16*$B$10
A21: Free Cash Flow | B21: =B18+B19+B20 | C21: =C18+C19+C20 | D21: =D18+D19+D20 | E21: =E18+E19+E20 | F21: =F18+F19+F20
A23: Discount Factor | B23: =1/(1+$B$11)^1 | C23: =1/(1+$B$11)^2 | D23: =1/(1+$B$11)^3 | E23: =1/(1+$B$11)^4 | F23: =1/(1+$B$11)^5
A24: PV of FCF | B24: =B21*B23 | C24: =C21*C23 | D24: =D21*D23 | E24: =E21*E23 | F24: =F21*F23
A26: Terminal Value (Year 5) | B26: =F21*(1+$B$12)/($B$11-$B$12)
A27: PV of Terminal Value | B27: =B26*F23
A29: Enterprise Value | B29: =SUM(B24:F24)+B27

Sheet D3 Best Practices
A1: D3 · Dashboard & Modeling Best Practices
A2: The standard color convention, applied.
A5: Blue text | B5: A hardcoded input — e.g. a growth rate you typed in
A6: Black text | B6: A formula referencing other cells on this sheet
A7: Green text | B7: A formula linking to a different sheet
A9: Example: revenue growth assumption
A10: Growth rate | B10: 0.08
A11: Prior revenue | B11: 1000
A12: This year's revenue (=B11*(1+B10)) | B12: =B11*(1+B10)
A14: Example: safe division with IFERROR
A15: Net income | B15: 0
A16: Shares outstanding | B16: 0
A17: EPS (=IFERROR(NI/shares,"n/a")) | B17: =IFERROR(B15/B16,"n/a")
A19: Notice EPS shows "n/a" instead of a #DIV/0! error, because shares outstanding is 0 above — try changing B16 to see it recalculate normally.
